airtable_view_fetcher/__init__.py
airtable_view_fetcher/fetch_airtable_data.py
airtable_view_fetcher-0.4.0.dist-info/LICENSE
airtable_view_fetcher-0.4.0.dist-info/METADATA
airtable_view_fetcher-0.4.0.dist-info/WHEEL
airtable_view_fetcher-0.4.0.dist-info/entry_points.txt
airtable_view_fetcher-0.4.0.dist-info/top_level.txt
airtable_view_fetcher-0.4.0.dist-info/RECORD
