Metadata-Version: 2.1
Name: airtable-view-fetcher
Version: 0.4.0
Summary: Tool to scrape data from an Airtable shared view
Home-page: https://github.com/vartur/airtable_view_fetcher
Author: Vincent Artur
Author-email: 6145191+vartur@users.noreply.github.com
License-File: LICENSE
Requires-Dist: requests
Requires-Dist: pytz
